falkor/__init__.py
falkor/main.py
falkor-0.0.2.dist-info/LICENSE
falkor-0.0.2.dist-info/METADATA
falkor-0.0.2.dist-info/WHEEL
falkor-0.0.2.dist-info/entry_points.txt
falkor-0.0.2.dist-info/top_level.txt
falkor-0.0.2.dist-info/RECORD
